{
  "manifestVersion": "3.1",
  "impls": {
    "ac0db523ddc3e330f735df7b3b0b24460531c71290a891170e840f8f67d5ff6b": {
      "address": "0x4F7c0D01eB71B7478EDE128DF2A088f5a22011fC",
      "txHash": "0xa66dfa437263e79244f49d3f3036c660020daf58409db190c0fde2b57af45970",
      "layout": {
        "storage": [],
        "types": {}
      }
    },
    "7b5db5834058ee2abe0d5002cdc7717d03a3f4ef1e721619ba3f1fe09dac5bef": {
      "address": "0xCfc8Fa3c44a269C1698978907793e8AA9a532B9b",
      "txHash": "0xef2dc61d85b7dc2180a88e94ae9f55809eb3ab4b1bf8d8b82b2b26b0464eb8d7",
      "layout": {
        "storage": [
          {
            "contract": "Initializable",
            "label": "_initialized",
            "type": "t_bool",
            "src": "../@openzeppelin/contracts-upgradeable/proxy/Initializable.sol:25"
          },
          {
            "contract": "Initializable",
            "label": "_initializing",
            "type": "t_bool",
            "src": "../@openzeppelin/contracts-upgradeable/proxy/Initializable.sol:30"
          },
          {
            "contract": "ContextUpgradeable",
            "label": "__gap",
            "type": "t_array(t_uint256)50_storage",
            "src": "../@openzeppelin/contracts-upgradeable/utils/ContextUpgradeable.sol:31"
          },
          {
            "contract": "ERC20Upgradeable",
            "label": "_balances",
            "type": "t_mapping(t_address,t_uint256)",
            "src": "../@openzeppelin/contracts-upgradeable/token/ERC20/ERC20Upgradeable.sol:37"
          },
          {
            "contract": "ERC20Upgradeable",
            "label": "_allowances",
            "type": "t_mapping(t_address,t_mapping(t_address,t_uint256))",
            "src": "../@openzeppelin/contracts-upgradeable/token/ERC20/ERC20Upgradeable.sol:39"
          },
          {
            "contract": "ERC20Upgradeable",
            "label": "_totalSupply",
            "type": "t_uint256",
            "src": "../@openzeppelin/contracts-upgradeable/token/ERC20/ERC20Upgradeable.sol:41"
          },
          {
            "contract": "ERC20Upgradeable",
            "label": "_name",
            "type": "t_string_storage",
            "src": "../@openzeppelin/contracts-upgradeable/token/ERC20/ERC20Upgradeable.sol:43"
          },
          {
            "contract": "ERC20Upgradeable",
            "label": "_symbol",
            "type": "t_string_storage",
            "src": "../@openzeppelin/contracts-upgradeable/token/ERC20/ERC20Upgradeable.sol:44"
          },
          {
            "contract": "ERC20Upgradeable",
            "label": "_decimals",
            "type": "t_uint8",
            "src": "../@openzeppelin/contracts-upgradeable/token/ERC20/ERC20Upgradeable.sol:45"
          },
          {
            "contract": "ERC20Upgradeable",
            "label": "__gap",
            "type": "t_array(t_uint256)44_storage",
            "src": "../@openzeppelin/contracts-upgradeable/token/ERC20/ERC20Upgradeable.sol:312"
          },
          {
            "contract": "Token",
            "label": "distributor",
            "type": "t_address",
            "src": "Token.sol:9"
          },
          {
            "contract": "Token",
            "label": "isLocked",
            "type": "t_bool",
            "src": "Token.sol:10"
          },
          {
            "contract": "Token",
            "label": "__gap",
            "type": "t_array(t_uint256)48_storage",
            "src": "Token.sol:57"
          }
        ],
        "types": {
          "t_address": {
            "label": "address"
          },
          "t_bool": {
            "label": "bool"
          },
          "t_array(t_uint256)48_storage": {
            "label": "uint256[48]"
          },
          "t_uint256": {
            "label": "uint256"
          },
          "t_mapping(t_address,t_uint256)": {
            "label": "mapping(address => uint256)"
          },
          "t_mapping(t_address,t_mapping(t_address,t_uint256))": {
            "label": "mapping(address => mapping(address => uint256))"
          },
          "t_string_storage": {
            "label": "string"
          },
          "t_uint8": {
            "label": "uint8"
          },
          "t_array(t_uint256)44_storage": {
            "label": "uint256[44]"
          },
          "t_array(t_uint256)50_storage": {
            "label": "uint256[50]"
          }
        }
      }
    },
    "19364cf8992cc6859e497fd0b98736ab126828fa3f77f08cc4764b4d034dc1aa": {
      "address": "0xB185268038961069b115cF1f46655A8ECE52D7B5",
      "txHash": "0x49cb7293592bbec6a5b3598d6797266454fbd1531854f8a4b46081c49856ccbd",
      "layout": {
        "storage": [
          {
            "contract": "Initializable",
            "label": "_initialized",
            "type": "t_bool",
            "src": "../@openzeppelin/contracts-upgradeable/proxy/Initializable.sol:25"
          },
          {
            "contract": "Initializable",
            "label": "_initializing",
            "type": "t_bool",
            "src": "../@openzeppelin/contracts-upgradeable/proxy/Initializable.sol:30"
          },
          {
            "contract": "ContextUpgradeable",
            "label": "__gap",
            "type": "t_array(t_uint256)50_storage",
            "src": "../@openzeppelin/contracts-upgradeable/utils/ContextUpgradeable.sol:31"
          },
          {
            "contract": "ERC20Upgradeable",
            "label": "_balances",
            "type": "t_mapping(t_address,t_uint256)",
            "src": "../@openzeppelin/contracts-upgradeable/token/ERC20/ERC20Upgradeable.sol:37"
          },
          {
            "contract": "ERC20Upgradeable",
            "label": "_allowances",
            "type": "t_mapping(t_address,t_mapping(t_address,t_uint256))",
            "src": "../@openzeppelin/contracts-upgradeable/token/ERC20/ERC20Upgradeable.sol:39"
          },
          {
            "contract": "ERC20Upgradeable",
            "label": "_totalSupply",
            "type": "t_uint256",
            "src": "../@openzeppelin/contracts-upgradeable/token/ERC20/ERC20Upgradeable.sol:41"
          },
          {
            "contract": "ERC20Upgradeable",
            "label": "_name",
            "type": "t_string_storage",
            "src": "../@openzeppelin/contracts-upgradeable/token/ERC20/ERC20Upgradeable.sol:43"
          },
          {
            "contract": "ERC20Upgradeable",
            "label": "_symbol",
            "type": "t_string_storage",
            "src": "../@openzeppelin/contracts-upgradeable/token/ERC20/ERC20Upgradeable.sol:44"
          },
          {
            "contract": "ERC20Upgradeable",
            "label": "_decimals",
            "type": "t_uint8",
            "src": "../@openzeppelin/contracts-upgradeable/token/ERC20/ERC20Upgradeable.sol:45"
          },
          {
            "contract": "ERC20Upgradeable",
            "label": "__gap",
            "type": "t_array(t_uint256)44_storage",
            "src": "../@openzeppelin/contracts-upgradeable/token/ERC20/ERC20Upgradeable.sol:312"
          },
          {
            "contract": "Token",
            "label": "distributor",
            "type": "t_address",
            "src": "Token.sol:9"
          },
          {
            "contract": "Token",
            "label": "isLocked",
            "type": "t_bool",
            "src": "Token.sol:10"
          },
          {
            "contract": "Token",
            "label": "__gap",
            "type": "t_array(t_uint256)48_storage",
            "src": "Token.sol:57"
          }
        ],
        "types": {
          "t_address": {
            "label": "address"
          },
          "t_bool": {
            "label": "bool"
          },
          "t_array(t_uint256)48_storage": {
            "label": "uint256[48]"
          },
          "t_uint256": {
            "label": "uint256"
          },
          "t_mapping(t_address,t_uint256)": {
            "label": "mapping(address => uint256)"
          },
          "t_mapping(t_address,t_mapping(t_address,t_uint256))": {
            "label": "mapping(address => mapping(address => uint256))"
          },
          "t_string_storage": {
            "label": "string"
          },
          "t_uint8": {
            "label": "uint8"
          },
          "t_array(t_uint256)44_storage": {
            "label": "uint256[44]"
          },
          "t_array(t_uint256)50_storage": {
            "label": "uint256[50]"
          }
        }
      }
    },
    "7cefac90cc5d48e44cca7077c88c7c79d2c1d9d3dc8153ef30c710a048017389": {
      "address": "0xbBf2488d2dBbF9386772A77a0406A95B1Ff94E02",
      "txHash": "0x54927e6478a788455ef2853a677a81c3d0e98b53fb5727ed7f0182c4b58734dc",
      "layout": {
        "storage": [
          {
            "contract": "Initializable",
            "label": "_initialized",
            "type": "t_bool",
            "src": "../@openzeppelin/contracts-upgradeable/proxy/Initializable.sol:25"
          },
          {
            "contract": "Initializable",
            "label": "_initializing",
            "type": "t_bool",
            "src": "../@openzeppelin/contracts-upgradeable/proxy/Initializable.sol:30"
          },
          {
            "contract": "ContextUpgradeable",
            "label": "__gap",
            "type": "t_array(t_uint256)50_storage",
            "src": "../@openzeppelin/contracts-upgradeable/utils/ContextUpgradeable.sol:31"
          },
          {
            "contract": "ERC20Upgradeable",
            "label": "_balances",
            "type": "t_mapping(t_address,t_uint256)",
            "src": "../@openzeppelin/contracts-upgradeable/token/ERC20/ERC20Upgradeable.sol:37"
          },
          {
            "contract": "ERC20Upgradeable",
            "label": "_allowances",
            "type": "t_mapping(t_address,t_mapping(t_address,t_uint256))",
            "src": "../@openzeppelin/contracts-upgradeable/token/ERC20/ERC20Upgradeable.sol:39"
          },
          {
            "contract": "ERC20Upgradeable",
            "label": "_totalSupply",
            "type": "t_uint256",
            "src": "../@openzeppelin/contracts-upgradeable/token/ERC20/ERC20Upgradeable.sol:41"
          },
          {
            "contract": "ERC20Upgradeable",
            "label": "_name",
            "type": "t_string_storage",
            "src": "../@openzeppelin/contracts-upgradeable/token/ERC20/ERC20Upgradeable.sol:43"
          },
          {
            "contract": "ERC20Upgradeable",
            "label": "_symbol",
            "type": "t_string_storage",
            "src": "../@openzeppelin/contracts-upgradeable/token/ERC20/ERC20Upgradeable.sol:44"
          },
          {
            "contract": "ERC20Upgradeable",
            "label": "_decimals",
            "type": "t_uint8",
            "src": "../@openzeppelin/contracts-upgradeable/token/ERC20/ERC20Upgradeable.sol:45"
          },
          {
            "contract": "ERC20Upgradeable",
            "label": "__gap",
            "type": "t_array(t_uint256)44_storage",
            "src": "../@openzeppelin/contracts-upgradeable/token/ERC20/ERC20Upgradeable.sol:312"
          },
          {
            "contract": "Token",
            "label": "distributor",
            "type": "t_address",
            "src": "Token.sol:9"
          },
          {
            "contract": "Token",
            "label": "isLocked",
            "type": "t_bool",
            "src": "Token.sol:10"
          },
          {
            "contract": "Token",
            "label": "__gap",
            "type": "t_array(t_uint256)48_storage",
            "src": "Token.sol:62"
          }
        ],
        "types": {
          "t_address": {
            "label": "address"
          },
          "t_bool": {
            "label": "bool"
          },
          "t_array(t_uint256)48_storage": {
            "label": "uint256[48]"
          },
          "t_uint256": {
            "label": "uint256"
          },
          "t_mapping(t_address,t_uint256)": {
            "label": "mapping(address => uint256)"
          },
          "t_mapping(t_address,t_mapping(t_address,t_uint256))": {
            "label": "mapping(address => mapping(address => uint256))"
          },
          "t_string_storage": {
            "label": "string"
          },
          "t_uint8": {
            "label": "uint8"
          },
          "t_array(t_uint256)44_storage": {
            "label": "uint256[44]"
          },
          "t_array(t_uint256)50_storage": {
            "label": "uint256[50]"
          }
        }
      }
    }
  },
  "admin": {
    "address": "0x3e6F4E6cfD9B46fa6a6Bd908867ba1011ad221ba",
    "txHash": "0x480da4913cd62e8a18783c79f1099a692eb4e5d045d508c3a83aaad5f8d3c94a"
  }
}
